{"version": 2.0, "questions": [{"question": "Which analytical technique is implemented to identify solubility.", "answers": {"a": "UV analysis", "b": "HPLC", "c": "GC", "d": "Titration"}, "explanations": {"a": "", "b": "", "c": "", "d": ""}, "correctAnswer": "a", "difficulty": "beginner"}, {"question": "What is the correct way to introduce solute into system", "answers": {"a": "Continuously add specific amount at specific time interval", "b": "Add excess quantity in advance", "c": "Add small quantity and allow it to dissolved before adding more", "d": "Gradually decrease quantity of solute added with time"}, "explanations": {"a": "", "b": "", "c": "", "d": ""}, "correctAnswer": "c", "difficulty": "beginner"}, {"question": "What will be the allowable R<sup>2</sup> value during calibration", "answers": {"a": "<0.9", "b": ">0.9", "c": ">0.99", "d": "=0"}, "explanations": {"a": "", "b": "", "c": "", "d": ""}, "correctAnswer": "c", "difficulty": "beginner"}, {"question": "What is the general trend observed between solubility and temperature", "answers": {"a": "Increase with temperature", "b": "Decrease with temperature", "c": "Remain constant", "d": "First increase then decrease"}, "explanations": {"a": "", "b": "", "c": "", "d": ""}, "correctAnswer": "a", "difficulty": "beginner"}]}